vot/__init__.py
vot/__main__.py
vot/version.py
vot/analysis/__init__.py
vot/analysis/accuracy.py
vot/analysis/failures.py
vot/analysis/longterm.py
vot/analysis/multistart.py
vot/analysis/processor.py
vot/analysis/supervised.py
vot/analysis/tests.py
vot/dataset/__init__.py
vot/dataset/common.py
vot/dataset/cow.png
vot/dataset/dummy.py
vot/dataset/got10k.py
vot/dataset/otb.py
vot/dataset/proxy.py
vot/dataset/trackingnet.py
vot/experiment/__init__.py
vot/experiment/helpers.py
vot/experiment/multirun.py
vot/experiment/multistart.py
vot/experiment/transformer.py
vot/region/__init__.py
vot/region/io.py
vot/region/raster.py
vot/region/shapes.py
vot/region/tests.py
vot/report/__init__.py
vot/report/commands.tex
vot/report/common.py
vot/report/html.py
vot/report/jquery.js
vot/report/latex.py
vot/report/pure.css
vot/report/report.css
vot/report/report.js
vot/report/table.js
vot/report/tests.py
vot/report/video.py
vot/stack/__init__.py
vot/stack/otb100.yaml
vot/stack/otb50.yaml
vot/stack/tests.py
vot/stack/vot2013.yaml
vot/stack/vot2014.yaml
vot/stack/vot2017.yaml
vot/stack/vots2023.yaml
vot/stack/tests/basic.yaml
vot/stack/tests/multiobject.yaml
vot/stack/tests/segmentation.yaml
vot/stack/vot2015/rgb.yaml
vot/stack/vot2015/tir.yaml
vot/stack/vot2016/rgb.yaml
vot/stack/vot2016/tir.yaml
vot/stack/vot2018/longterm.yaml
vot/stack/vot2018/shortterm.yaml
vot/stack/vot2019/longterm.yaml
vot/stack/vot2019/rgbd.yaml
vot/stack/vot2019/rgbtir.yaml
vot/stack/vot2019/shortterm.yaml
vot/stack/vot2020/longterm.yaml
vot/stack/vot2020/rgbd.yaml
vot/stack/vot2020/rgbtir.yaml
vot/stack/vot2020/shortterm.yaml
vot/stack/vot2021/longterm.yaml
vot/stack/vot2021/rgbd.yaml
vot/stack/vot2021/shortterm.yaml
vot/stack/vot2022/depth.yaml
vot/stack/vot2022/longterm.yaml
vot/stack/vot2022/rgbd.yaml
vot/stack/vot2022/shortterm.yaml
vot/stack/vot2022/shorttermbox.yaml
vot/stack/vots2024/main.yaml
vot/stack/vots2024/votst.yaml
vot/stack/vots2024/votstval.yaml
vot/stack/vots2025/main.yaml
vot_toolkit-0.7.4.dist-info/LICENSE
vot_toolkit-0.7.4.dist-info/METADATA
vot_toolkit-0.7.4.dist-info/WHEEL
vot_toolkit-0.7.4.dist-info/entry_points.txt
vot_toolkit-0.7.4.dist-info/top_level.txt
vot_toolkit-0.7.4.dist-info/RECORD
