Metadata-Version: 2.1
Name: vot-toolkit
Version: 0.7.4
Summary: Perform visual object tracking experiments and analyze results
Home-page: https://github.com/votchallenge/toolkit
Author: Luka Cehovin Zajc
Author-email: luka.cehovin@gmail.com
Classifier: Programming Language :: Python :: 3
Classifier: License :: OSI Approved :: GNU General Public License v3 (GPLv3)
Classifier: Operating System :: OS Independent
Classifier: Development Status :: 4 - Beta
Classifier: Intended Audience :: Science/Research
Requires-Python: >=3.7
License-File: LICENSE
Requires-Dist: vot-trax >=4.0.1
Requires-Dist: tqdm >=4.37
Requires-Dist: numpy >=1.16
Requires-Dist: opencv-python >=4.0
Requires-Dist: six
Requires-Dist: pylatex >=1.3
Requires-Dist: jsonschema >=3.2
Requires-Dist: pyYAML >=5.3
Requires-Dist: matplotlib >=3.0
Requires-Dist: Pillow >=7.0
Requires-Dist: numba >=0.47
Requires-Dist: requests >=2.22
Requires-Dist: colorama >=0.4.3
Requires-Dist: packaging >=20
Requires-Dist: dominate >=2.5
Requires-Dist: cachetools >=4.1
Requires-Dist: bidict >=0.19
Requires-Dist: phx-class-registry >=5.0
Requires-Dist: attributee >=0.1.8
Requires-Dist: lazy-object-proxy >=1.9
Provides-Extra: jupyter
Requires-Dist: ipywidgets ; extra == 'jupyter'
Requires-Dist: jupyter ; extra == 'jupyter'
Requires-Dist: itables ; extra == 'jupyter'
